nepali_toolkit/__init__.py
nepali_toolkit/__main__.py
nepali_toolkit/_version.py
nepali_toolkit/exceptions.py
nepali_toolkit/log.py
nepali_toolkit/bs/__init__.py
nepali_toolkit/bs/calendar.py
nepali_toolkit/bs/dataset.py
nepali_toolkit/bs/types.py
nepali_toolkit/bs/data/bs_years_2077_2082.json
nepali_toolkit/bs/data/holidays_bs_2082.json
nepali_toolkit/common/i18n.py
nepali_toolkit/common/util.py
nepali_toolkit/gazetteer/__init__.py
nepali_toolkit/gazetteer/gazetteer.py
nepali_toolkit/gazetteer/models.py
nepali_toolkit/gazetteer/data/districts.json
nepali_toolkit/gazetteer/data/places.json
nepali_toolkit/gazetteer/data/provinces.json
nepali_toolkit/gazetteer/data/zones.json
nepali_toolkit/holiday/__init__.py
nepali_toolkit/holiday/holidays.py
nepali_toolkit/holiday/data/holidays_bs_2082.json
nepali_toolkit/scripts/alphabet/__init__.py
nepali_toolkit/scripts/alphabet/alphabets.py
nepali_toolkit/scripts/barakhari/__init__.py
nepali_toolkit/scripts/barakhari/barakhari.py
nepali_toolkit/scripts/data/translit_data.json
nepali_toolkit/scripts/translator/__init__.py
nepali_toolkit/scripts/translator/transliterate.py
nepali_toolkit/trek/__init__.py
nepali_toolkit/trek/catalog.py
nepali_toolkit/trek/models.py
nepali_toolkit/trek/data/treks.json
nepali_toolkit/units/__init__.py
nepali_toolkit/units/converter.py
nepali_toolkit/units/profiles.py
nepali_toolkits-1.0.0.dist-info/licenses/LICENSE
nepali_toolkits-1.0.0.dist-info/METADATA
nepali_toolkits-1.0.0.dist-info/WHEEL
nepali_toolkits-1.0.0.dist-info/top_level.txt
nepali_toolkits-1.0.0.dist-info/RECORD
