Metadata-Version: 2.4
Name: nepali-toolkits
Version: 1.0.0
Summary: Production-ready utilities for Nepali: BS calendar & holidays, script tools, gazetteer, units, treks.
Home-page: https://github.com/yourorg/nepali-toolkit
Author: Sujit Khanal
Author-email: Sujit Khanal <thesujitkhanal@gmail.com>
License: MIT
Project-URL: Homepage, https://github.com/sujit-codezen/nepali_toolkit
Project-URL: Bug Tracker, https://github.com/sujit-codezen/nepali_toolkit/issues
Project-URL: Source, https://github.com/sujit-codezen/nepali_toolkit
Classifier: Development Status :: 4 - Beta
Classifier: Intended Audience :: Developers
Classifier: License :: OSI Approved :: MIT License
Classifier: Programming Language :: Python :: 3
Classifier: Programming Language :: Python :: 3 :: Only
Classifier: Programming Language :: Python :: 3.9
Classifier: Topic :: Software Development :: Libraries
Classifier: Topic :: Text Processing :: Linguistic
Classifier: Natural Language :: English
Classifier: Natural Language :: Nepali
Requires-Python: >=3.9
License-File: LICENSE
Requires-Dist: python-dateutil>=2.8.2
Requires-Dist: pytz>=2024.1
Requires-Dist: regex>=2024.5.15
Requires-Dist: pydantic>=2.7
Provides-Extra: dev
Requires-Dist: pytest>=7.0; extra == "dev"
Requires-Dist: pytest-cov>=4.0; extra == "dev"
Requires-Dist: mypy>=1.0; extra == "dev"
Requires-Dist: ruff>=0.4; extra == "dev"
Requires-Dist: build>=1.0; extra == "dev"
Requires-Dist: twine>=4.0; extra == "dev"
Dynamic: author
Dynamic: home-page
Dynamic: license-file
Dynamic: requires-python
